odoo/addons/l10n_th_gov_purchase_request/README.rst
odoo/addons/l10n_th_gov_purchase_request/__init__.py
odoo/addons/l10n_th_gov_purchase_request/__manifest__.py
odoo/addons/l10n_th_gov_purchase_request/data/procurement_method.xml
odoo/addons/l10n_th_gov_purchase_request/data/procurement_type.xml
odoo/addons/l10n_th_gov_purchase_request/data/purchase_exception.xml
odoo/addons/l10n_th_gov_purchase_request/data/purchase_request_exception.xml
odoo/addons/l10n_th_gov_purchase_request/data/purchase_request_substate.xml
odoo/addons/l10n_th_gov_purchase_request/data/purchase_type.xml
odoo/addons/l10n_th_gov_purchase_request/i18n/l10n_th_gov_purchase_request.pot
odoo/addons/l10n_th_gov_purchase_request/models/__init__.py
odoo/addons/l10n_th_gov_purchase_request/models/procurement_committee.py
odoo/addons/l10n_th_gov_purchase_request/models/procurement_method.py
odoo/addons/l10n_th_gov_purchase_request/models/procurement_type.py
odoo/addons/l10n_th_gov_purchase_request/models/purchase_request.py
odoo/addons/l10n_th_gov_purchase_request/models/purchase_request_line.py
odoo/addons/l10n_th_gov_purchase_request/models/purchase_type.py
odoo/addons/l10n_th_gov_purchase_request/readme/CONFIGURATION.rst
odoo/addons/l10n_th_gov_purchase_request/readme/CONTRIBUTORS.rst
odoo/addons/l10n_th_gov_purchase_request/readme/DESCRIPTION.rst
odoo/addons/l10n_th_gov_purchase_request/security/ir.model.access.csv
odoo/addons/l10n_th_gov_purchase_request/security/procurement_team.xml
odoo/addons/l10n_th_gov_purchase_request/static/description/icon.png
odoo/addons/l10n_th_gov_purchase_request/static/description/index.html
odoo/addons/l10n_th_gov_purchase_request/tests/__init__.py
odoo/addons/l10n_th_gov_purchase_request/tests/test_gov_purchase_request.py
odoo/addons/l10n_th_gov_purchase_request/views/procurement_method_views.xml
odoo/addons/l10n_th_gov_purchase_request/views/procurement_type_views.xml
odoo/addons/l10n_th_gov_purchase_request/views/purchase_request_views.xml
odoo_addon_l10n_th_gov_purchase_request-15.0.2.0.1.dist-info/METADATA
odoo_addon_l10n_th_gov_purchase_request-15.0.2.0.1.dist-info/WHEEL
odoo_addon_l10n_th_gov_purchase_request-15.0.2.0.1.dist-info/top_level.txt
odoo_addon_l10n_th_gov_purchase_request-15.0.2.0.1.dist-info/RECORD
