Metadata-Version: 2.1
Name: odoo-addon-l10n-th-gov-purchase-request
Version: 15.0.2.0.1
Summary: Thai Localization - Government Purchase Request
Home-page: https://github.com/OCA/l10n-thailand
Author: Ecosoft, Odoo Community Association (OCA)
Author-email: support@odoo-community.org
License: AGPL-3
Platform: UNKNOWN
Classifier: Programming Language :: Python
Classifier: Framework :: Odoo
Classifier: Framework :: Odoo :: 15.0
Classifier: License :: OSI Approved :: GNU Affero General Public License v3
Classifier: Development Status :: 4 - Beta
Requires-Python: >=3.8
Requires-Dist: odoo-addon-purchase-exception <15.1dev,>=15.0dev
Requires-Dist: odoo-addon-purchase-request-exception <15.1dev,>=15.0dev
Requires-Dist: odoo-addon-purchase-request-substate <15.1dev,>=15.0dev
Requires-Dist: odoo-addon-purchase-request-to-requisition <15.1dev,>=15.0dev
Requires-Dist: odoo <15.1dev,>=15.0a
